LICENSE
README.md
setup.py
cloudify_aws/__init__.py
cloudify_aws/__version__.py
cloudify_aws/autoscaling/__init__.py
cloudify_aws/autoscaling/resources/__init__.py
cloudify_aws/autoscaling/resources/autoscaling_group.py
cloudify_aws/autoscaling/resources/launch_configuration.py
cloudify_aws/autoscaling/resources/lifecycle_hook.py
cloudify_aws/autoscaling/resources/notification_configuration.py
cloudify_aws/autoscaling/resources/policy.py
cloudify_aws/autoscaling/tests/__init__.py
cloudify_aws/autoscaling/tests/test_autoscaling_group.py
cloudify_aws/autoscaling/tests/test_autoscalingbase.py
cloudify_aws/autoscaling/tests/test_launch_configuration.py
cloudify_aws/autoscaling/tests/test_lifecycle_hook.py
cloudify_aws/autoscaling/tests/test_policy.py
cloudify_aws/cloudformation/__init__.py
cloudify_aws/cloudformation/resources/__init__.py
cloudify_aws/cloudformation/resources/stack.py
cloudify_aws/cloudformation/tests/__init__.py
cloudify_aws/cloudformation/tests/test_stack.py
cloudify_aws/cloudwatch/__init__.py
cloudify_aws/cloudwatch/resources/__init__.py
cloudify_aws/cloudwatch/resources/alarm.py
cloudify_aws/cloudwatch/resources/event.py
cloudify_aws/cloudwatch/resources/rule.py
cloudify_aws/cloudwatch/resources/target.py
cloudify_aws/cloudwatch/tests/__init__.py
cloudify_aws/cloudwatch/tests/test_alarm.py
cloudify_aws/cloudwatch/tests/test_cloudwatchbase.py
cloudify_aws/cloudwatch/tests/test_event.py
cloudify_aws/cloudwatch/tests/test_rule.py
cloudify_aws/cloudwatch/tests/test_target.py
cloudify_aws/codepipeline/__init__.py
cloudify_aws/codepipeline/resources/__init__.py
cloudify_aws/codepipeline/resources/pipeline.py
cloudify_aws/codepipeline/tests/__init__.py
cloudify_aws/codepipeline/tests/test_pipeline.py
cloudify_aws/cognito/__init__.py
cloudify_aws/cognito/resources/__init__.py
cloudify_aws/cognito/resources/identity_pool.py
cloudify_aws/cognito/resources/identity_provider.py
cloudify_aws/cognito/resources/user_pool.py
cloudify_aws_plugin.egg-info/PKG-INFO
cloudify_aws_plugin.egg-info/SOURCES.txt
cloudify_aws_plugin.egg-info/dependency_links.txt
cloudify_aws_plugin.egg-info/requires.txt
cloudify_aws_plugin.egg-info/top_level.txt
