Metadata-Version: 2.1
Name: cloudify-aws-plugin
Version: 3.1.7
Summary: A Cloudify plugin for AWS
Author: Cloudify Platform Ltd.
Author-email: hello@cloudify.co
License: LICENSE
License-File: LICENSE
